shifter.v
module shifter(data, shamt, direction, outp);
//direction
//1 = right
//0 = left
input [3: 0] data;
input [1: 0] shamt;
input direction;
output [3: 0] outp;

assign outp = (direction)? (data >> shamt) : (data << shamt);

endmodule

fulladder.v
module fulladder(A, B, cin, sum, cout);
input A, B, cin;
output sum;
output cout;

assign sum = A ^ B ^ cin;
assign cout = (A & B) | (A & cin) | (B & cin);

endmodule

adder_subtractor.v
module adder_subtractor(X, Y, cout, G, S);
input [3: 0] X, Y;
input [2: 0] S;
output [3: 0] G;
output cout;

wire [3: 0] to_A;
wire [2: 0] c;

assign to_A[3] = (Y[3] & S[1]) | ((~Y[3]) & S[2]);
assign to_A[2] = (Y[2] & S[1]) | ((~Y[2]) & S[2]);
assign to_A[1] = (Y[1] & S[1]) | ((~Y[1]) & S[2]);
assign to_A[0] = (Y[0] & S[1]) | ((~Y[0]) & S[2]);

fulladder fulladder3(.A(to_A[3]),.B(X[3]), .cin(c[2]),.cout(cout),.sum(G[3]));
fulladder fulladder2(.A(to_A[2]),.B(X[2]), .cin(c[1]),.cout(c[2]),.sum(G[2]));
fulladder fulladder1(.A(to_A[1]),.B(X[1]), .cin(c[0]),.cout(c[1]),.sum(G[1]));
fulladder fulladder0(.A(to_A[0]),.B(X[0]), .cin(S[0]),.cout(c[0]),.sum(G[0]));

endmodule

alu.v
module alu(X, Y, S, d, shamt, cout, outp);
input [3: 0] X, Y;
input [2: 0] S;
input [1: 0] shamt;
input d;
output [3: 0] outp;
output cout;

wire [3: 0] sum;

adder_subtractor add_sub1(.X(X), .Y(Y), .cout(cout), .G(sum), .S(S));
shifter shift(.data(sum), .shamt(shamt), .direction(d), .outp(outp));

endmodule

alu_tb.v
`timescale 1ns / 1ps;
module alu_tb;

reg [3: 0]X, Y;;
reg [2: 0] S;
reg [1: 0] shamt;
reg d;

wire [3: 0] outp;

alu dut(.X(X), .Y(Y), .S(S), .d(d), .shamt(shamt), .cout(cout), .outp(outp));

initial begin
    $dumpfile("alu.vcd");
    $dumpvars(0, alu_tb);
    $monitor("X = %4b, Y = %4b, S = %3b shamt = %2b, d = %b, cout = %b, outp = %4b", X, Y, S, shamt, d, cout, outp);
end

integer i;
initial begin
    for(i = 0; i < 16384; i = i + 1) begin
        {X, Y, S, shamt, d} = i;
        #1;
    end
end
endmodule

alu.vcd
$date
	Mon Oct 13 20:25:46 2025
$end
$version
	Icarus Verilog
$end
$timescale
	1ps
$end
$scope module alu_tb $end
$var wire 4 ! outp [3:0] $end
$var wire 1 " cout $end
$var reg 3 # S [2:0] $end
$var reg 4 $ X [3:0] $end
$var reg 4 % Y [3:0] $end
$var reg 1 & d $end
$var reg 2 ' shamt [1:0] $end
$var integer 32 ( i [31:0] $end
$scope module dut $end
$var wire 3 ) S [2:0] $end
$var wire 4 * X [3:0] $end
$var wire 4 + Y [3:0] $end
$var wire 1 & d $end
$var wire 2 , shamt [1:0] $end
$var wire 4 - sum [3:0] $end
$var wire 4 . outp [3:0] $end
$var wire 1 " cout $end
$scope module add_sub1 $end
$var wire 3 / S [2:0] $end
$var wire 4 0 X [3:0] $end
$var wire 4 1 Y [3:0] $end
$var wire 4 2 to_A [3:0] $end
$var wire 1 " cout $end
$var wire 3 3 c [2:0] $end
$var wire 4 4 G [3:0] $end
$scope module fulladder0 $end
$var wire 1 5 A $end
$var wire 1 6 B $end
$var wire 1 7 cin $end
$var wire 1 8 cout $end
$var wire 1 9 sum $end
$upscope $end
$scope module fulladder1 $end
$var wire 1 : A $end
$var wire 1 ; B $end
$var wire 1 < cin $end
$var wire 1 = cout $end
$var wire 1 > sum $end
$upscope $end
$scope module fulladder2 $end
$var wire 1 ? A $end
$var wire 1 @ B $end
$var wire 1 A cin $end
$var wire 1 B cout $end
$var wire 1 C sum $end
$upscope $end
$scope module fulladder3 $end
$var wire 1 D A $end
$var wire 1 E B $end
$var wire 1 F cin $end
$var wire 1 " cout $end
$var wire 1 G sum $end
$upscope $end
$upscope $end
$scope module shift $end
$var wire 4 H data [3:0] $end
$var wire 1 & direction $end
$var wire 2 I shamt [1:0] $end
$var wire 4 J outp [3:0] $end
$upscope $end
$upscope $end
$upscope $end
$enddefinitions $end
$comment Show the parameter values. $end
$dumpall
$end
#0
$dumpvars
b0 J
b0 I
b0 H
0G
0F
0E
0D
0C
0B
0A
0@
0?
0>
0=
0<
0;
0:
09
08
07
06
05
b0 4
b0 3
b0 2
b0 1
b0 0
b0 /
b0 .
b0 -
b0 ,
b0 +
b0 *
b0 )
b0 (
b0 '
0&
b0 %
b0 $
b0 #
0"
b0 !
$end
#1000
1&
b1 (
#2000
b1 '
b1 ,
b1 I
0&
b10 (
#3000
1&
b11 (
#4000
b10 '
b10 ,
b10 I
0&
b100 (
#5000
1&
b101 (
#6000
b11 '
b11 ,
b11 I
0&
b110 (
#7000
1&
b111 (
#8000
b1 !
b1 .
b1 J
b1 -
b1 4
b1 H
19
17
b1 #
b1 )
b1 /
b0 '
b0 ,
b0 I
0&
b1000 (
#9000
1&
b1001 (
#10000
b10 !
b10 .
b10 J
b1 '
b1 ,
b1 I
0&
b1010 (
#11000
b0 !
b0 .
b0 J
1&
b1011 (
#12000
b100 !
b100 .
b100 J
b10 '
b10 ,
b10 I
0&
b1100 (
#13000
b0 !
b0 .
b0 J
1&
b1101 (
#14000
b1000 !
b1000 .
b1000 J
b11 '
b11 ,
b11 I
0&
b1110 (
#15000
b0 !
b0 .
b0 J
1&
b1111 (
#16000
b0 -
b0 4
b0 H
09
07
b0 !
b0 .
b0 J
b10 #
b10 )
b10 /
b0 '
b0 ,
b0 I
0&
b10000 (
#17000
1&
b10001 (
#18000
b1 '
b1 ,
b1 I
0&
b10010 (
#19000
1&
b10011 (
#20000
b10 '
b10 ,
b10 I
0&
b10100 (
#21000
1&
b10101 (
#22000
b11 '
b11 ,
b11 I
0&
b10110 (
#23000
1&
b10111 (
#24000
b1 !
b1 .
b1 J
b1 -
b1 4
b1 H
19
17
b11 #
b11 )
b11 /
b0 '
b0 ,
b0 I
0&
b11000 (
#25000
1&
b11001 (
#26000
b10 !
b10 .
b10 J
b1 '
b1 ,
b1 I
0&
b11010 (
#27000
b0 !
b0 .
b0 J
1&
b11011 (
#28000
b100 !
b100 .
b100 J
b10 '
b10 ,
b10 I
0&
b11100 (
#29000
b0 !
b0 .
b0 J
1&
b11101 (
#30000
b1000 !
b1000 .
b1000 J
b11 '
b11 ,
b11 I
0&
b11110 (
#31000
b0 !
b0 .
b0 J
1&
b11111 (
#32000
1G
1C
1>
1D
1?
1:
15
b1111 2
b1111 -
b1111 4
b1111 H
19
07
b1111 !
b1111 .
b1111 J
b100 #
b100 )
b100 /
b0 '
b0 ,
b0 I
0&
b100000 (
#33000
1&
b100001 (
#34000
b1110 !
b1110 .
b1110 J
b1 '
b1 ,
b1 I
0&
b100010 (
#35000
b111 !
b111 .
b111 J
1&
b100011 (
#36000
b1100 !
b1100 .
b1100 J
b10 '
b10 ,
b10 I
0&
b100100 (
#37000
b11 !
b11 .
b11 J
1&
b100101 (
#38000
b1000 !
b1000 .
b1000 J
b11 '
b11 ,
b11 I
0&
b100110 (
#39000
b1 !
b1 .
b1 J
1&
b100111 (
#40000
1"
0G
1F
1B
0C
1A
1=
0>
1<
b111 3
18
b0 -
b0 4
b0 H
09
17
b0 !
b0 .
b0 J
b101 #
b101 )
b101 /
b0 '
b0 ,
b0 I
0&
b101000 (
#41000
1&
b101001 (
#42000
b1 '
b1 ,
b1 I
0&
b101010 (
#43000
1&
b101011 (
#44000
b10 '
b10 ,
b10 I
0&
b101100 (
#45000
1&
b101101 (
#46000
b11 '
b11 ,
b11 I
0&
b101110 (
#47000
1&
b101111 (
#48000
0"
1G
0F
0B
1C
0A
0=
1>
0<
b0 3
08
b1111 !
b1111 .
b1111 J
b1111 -
b1111 4
b1111 H
19
07
b110 #
b110 )
b110 /
b0 '
b0 ,
b0 I
0&
b110000 (
#49000
1&
b110001 (
#50000
b1110 !
b1110 .
b1110 J
b1 '
b1 ,
b1 I
0&
b110010 (
#51000
b111 !
b111 .
b111 J
1&
b110011 (
#52000
b1100 !
b1100 .
b1100 J
b10 '
b10 ,
b10 I
0&
b110100 (
#53000
b11 !
b11 .
b11 J
1&
b110101 (
#54000
b1000 !
b1000 .
b1000 J
b11 '
b11 ,
b11 I
0&
b110110 (
#55000
b1 !
b1 .
b1 J
1&
b110111 (
#56000
1"
0G
1F
1B
0C
1A
1=
0>
1<
b111 3
18
b0 -
b0 4
b0 H
09
17
b0 !
b0 .
b0 J
b111 #
b111 )
b111 /
b0 '
b0 ,
b0 I
0&
b111000 (
#57000
1&
b111001 (
#58000
b1 '
b1 ,
b1 I
0&
b111010 (
#59000
1&
b111011 (
#60000
b10 '
b10 ,
b10 I
0&
b111100 (
#61000
1&
b111101 (
#62000
b11 '
b11 ,
b11 I
0&
b111110 (
#63000
1&
b111111 (
#64000
0F
0A
0"
0B
0=
0G
0C
0<
0D
0?
0:
05
b0 3
08
b0 2
b0 !
b0 .
b0 J
b0 -
b0 4
b0 H
09
07
b1 %
b1 +
b1 1
b0 #
b0 )
b0 /
b0 '
b0 ,
b0 I
0&
b1000000 (
#65000
1&
b1000001 (
#66000
b1 '
b1 ,
b1 I
0&
b1000010 (
#67000
1&
b1000011 (
#68000
b10 '
b10 ,
b10 I
0&
b1000100 (
#69000
1&
b1000101 (
#70000
b11 '
b11 ,
b11 I
0&
b1000110 (
#71000
1&
b1000111 (
#72000
b1 !
b1 .
b1 J
b1 -
b1 4
b1 H
19
17
b1 #
b1 )
b1 /
b0 '
b0 ,
b0 I
0&
b1001000 (
#73000
1&
b1001001 (
#74000
b10 !
b10 .
b10 J
b1 '
b1 ,
b1 I
0&
b1001010 (
#75000
b0 !
b0 .
b0 J
1&
b1001011 (
#76000
b100 !
b100 .
b100 J
b10 '
b10 ,
b10 I
0&
b1001100 (
#77000
b0 !
b0 .
b0 J
1&
b1001101 (
#78000
b1000 !
b1000 .
b1000 J
b11 '
b11 ,
b11 I
0&
b1001110 (
#79000
b0 !
b0 .
b0 J
1&
b1001111 (
#80000
15
b1 2
b1 -
b1 4
b1 H
19
07
b1 !
b1 .
b1 J
b10 #
b10 )
b10 /
b0 '
b0 ,
b0 I
0&
b1010000 (
#81000
1&
b1010001 (
#82000
b10 !
b10 .
b10 J
b1 '
b1 ,
b1 I
0&
b1010010 (
#83000
b0 !
b0 .
b0 J
1&
b1010011 (
#84000
b100 !
b100 .
b100 J
b10 '
b10 ,
b10 I
0&
b1010100 (
#85000
b0 !
b0 .
b0 J
1&
b1010101 (
#86000
b1000 !
b1000 .
b1000 J
b11 '
b11 ,
b11 I
0&
b1010110 (
#87000
b0 !
b0 .
b0 J
1&
b1010111 (
#88000
1>
1<
b1 3
18
b10 -
b10 4
b10 H
09
17
b10 !
b10 .
b10 J
b11 #
b11 )
b11 /
b0 '
b0 ,
b0 I
0&
b1011000 (
#89000
1&
b1011001 (
#90000
b100 !
b100 .
b100 J
b1 '
b1 ,
b1 I
0&
b1011010 (
#91000
b1 !
b1 .
b1 J
1&
b1011011 (
#92000
b1000 !
b1000 .
b1000 J
b10 '
b10 ,
b10 I
0&
b1011100 (
#93000
b0 !
b0 .
b0 J
1&
b1011101 (
#94000
b11 '
b11 ,
b11 I
0&
b1011110 (
#95000
1&
b1011111 (
#96000
1G
1C
0<
1D
1?
1:
05
b0 3
08
b1110 2
b1110 -
b1110 4
b1110 H
09
07
b1110 !
b1110 .
b1110 J
b100 #
b100 )
b100 /
b0 '
b0 ,
b0 I
0&
b1100000 (
#97000
1&
b1100001 (
#98000
b1100 !
b1100 .
b1100 J
b1 '
b1 ,
b1 I
0&
b1100010 (
#99000
b111 !
b111 .
b111 J
1&
b1100011 (
#100000
b1000 !
b1000 .
b1000 J
b10 '
b10 ,
b10 I
0&
b1100100 (
#101000
b11 !
b11 .
b11 J
1&
b1100101 (
#102000
b0 !
b0 .
b0 J
b11 '
b11 ,
b11 I
0&
b1100110 (
#103000
b1 !
b1 .
b1 J
1&
b1100111 (
#104000
b1111 -
b1111 4
b1111 H
19
17
b1111 !
b1111 .
b1111 J
b101 #
b101 )
b101 /
b0 '
b0 ,
b0 I
0&
b1101000 (
#105000
1&
b1101001 (
#106000
b1110 !
b1110 .
b1110 J
b1 '
b1 ,
b1 I
0&
b1101010 (
#107000
b111 !
b111 .
b111 J
1&
b1101011 (
#108000
b1100 !
b1100 .
b1100 J
b10 '
b10 ,
b10 I
0&
b1101100 (
#109000
b11 !
b11 .
b11 J
1&
b1101101 (
#110000
b1000 !
b1000 .
b1000 J
b11 '
b11 ,
b11 I
0&
b1101110 (
#111000
b1 !
b1 .
b1 J
1&
b1101111 (
#112000
15
b1111 2
b1111 -
b1111 4
b1111 H
19
07
b1111 !
b1111 .
b1111 J
b110 #
b110 )
b110 /
b0 '
b0 ,
b0 I
0&
b1110000 (
#113000
1&
b1110001 (
#114000
b1110 !
b1110 .
b1110 J
b1 '
b1 ,
b1 I
0&
b1110010 (
#115000
b111 !
b111 .
b111 J
1&
b1110011 (
#116000
b1100 !
b1100 .
b1100 J
b10 '
b10 ,
b10 I
0&
b1110100 (
#117000
b11 !
b11 .
b11 J
1&
b1110101 (
#118000
b1000 !
b1000 .
b1000 J
b11 '
b11 ,
b11 I
0&
b1110110 (
#119000
b1 !
b1 .
b1 J
1&
b1110111 (
#120000
1"
0G
1F
1B
0C
1A
1=
0>
1<
b111 3
18
b0 -
b0 4
b0 H
09
17
b0 !
b0 .
b0 J
b111 #
b111 )
b111 /
b0 '
b0 ,
b0 I
0&
b1111000 (
#121000
1&
b1111001 (
#122000
b1 '
b1 ,
b1 I
0&
b1111010 (
#123000
1&
b1111011 (
#124000
b10 '
b10 ,
b10 I
0&
b1111100 (
#125000
1&
b1111101 (
#126000
b11 '
b11 ,
b11 I
0&
b1111110 (
#127000
1&
b1111111 (
#128000
0F
0A
0"
0B
0=
0G
0C
0<
0D
0?
0:
05
b0 3
08
b0 2
b0 !
b0 .
b0 J
b0 -
b0 4
b0 H
09
07
b10 %
b10 +
b10 1
b0 #
b0 )
b0 /
b0 '
b0 ,
b0 I
0&
b10000000 (
#129000
1&
b10000001 (
#130000
b1 '
b1 ,
b1 I
0&
b10000010 (
#131000
1&
b10000011 (
#132000
b10 '
b10 ,
b10 I
0&
b10000100 (
#133000
1&
b10000101 (
#134000
b11 '
b11 ,
b11 I
0&
b10000110 (
#135000
1&
b10000111 (
#136000
b1 !
b1 .
b1 J
b1 -
b1 4
b1 H
19
17
b1 #
b1 )
b1 /
b0 '
b0 ,
b0 I
0&
b10001000 (
#137000
1&
b10001001 (
#138000
b10 !
b10 .
b10 J
b1 '
b1 ,
b1 I
0&
b10001010 (
#139000
b0 !
b0 .
b0 J
1&
b10001011 (
#140000
b100 !
b100 .
b100 J
b10 '
b10 ,
b10 I
0&
b10001100 (
#141000
b0 !
b0 .
b0 J
1&
b10001101 (
#142000
b1000 !
b1000 .
b1000 J
b11 '
b11 ,
b11 I
0&
b10001110 (
#143000
b0 !
b0 .
b0 J
1&
b10001111 (
#144000
1>
1:
b10 2
b10 -
b10 4
b10 H
09
07
b10 !
b10 .
b10 J
b10 #
b10 )
b10 /
b0 '
b0 ,
b0 I
0&
b10010000 (
#145000
1&
b10010001 (
#146000
b100 !
b100 .
b100 J
b1 '
b1 ,
b1 I
0&
b10010010 (
#147000
b1 !
b1 .
b1 J
1&
b10010011 (
#148000
b1000 !
b1000 .
b1000 J
b10 '
b10 ,
b10 I
0&
b10010100 (
#149000
b0 !
b0 .
b0 J
1&
b10010101 (
#150000
b11 '
b11 ,
b11 I
0&
b10010110 (
#151000
1&
b10010111 (
#152000
b11 -
b11 4
b11 H
19
17
b11 !
b11 .
b11 J
b11 #
b11 )
b11 /
b0 '
b0 ,
b0 I
0&
b10011000 (
#153000
1&
b10011001 (
#154000
b110 !
b110 .
b110 J
b1 '
b1 ,
b1 I
0&
b10011010 (
#155000
b1 !
b1 .
b1 J
1&
b10011011 (
#156000
b1100 !
b1100 .
b1100 J
b10 '
b10 ,
b10 I
0&
b10011100 (
#157000
b0 !
b0 .
b0 J
1&
b10011101 (
#158000
b1000 !
b1000 .
b1000 J
b11 '
b11 ,
b11 I
0&
b10011110 (
#159000
b0 !
b0 .
b0 J
1&
b10011111 (
#160000
1G
1C
0>
1D
1?
0:
15
b1101 2
b1101 -
b1101 4
b1101 H
19
07
b1101 !
b1101 .
b1101 J
b100 #
b100 )
b100 /
b0 '
b0 ,
b0 I
0&
b10100000 (
#161000
1&
b10100001 (
#162000
b1010 !
b1010 .
b1010 J
b1 '
b1 ,
b1 I
0&
b10100010 (
#163000
b110 !
b110 .
b110 J
1&
b10100011 (
#164000
b100 !
b100 .
b100 J
b10 '
b10 ,
b10 I
0&
b10100100 (
#165000
b11 !
b11 .
b11 J
1&
b10100101 (
#166000
b1000 !
b1000 .
b1000 J
b11 '
b11 ,
b11 I
0&
b10100110 (
#167000
b1 !
b1 .
b1 J
1&
b10100111 (
#168000
1>
1<
b1 3
18
b1110 -
b1110 4
b1110 H
09
17
b1110 !
b1110 .
b1110 J
b101 #
b101 )
b101 /
b0 '
b0 ,
b0 I
0&
b10101000 (
#169000
1&
b10101001 (
#170000
b1100 !
b1100 .
b1100 J
b1 '
b1 ,
b1 I
0&
b10101010 (
#171000
b111 !
b111 .
b111 J
1&
b10101011 (
#172000
b1000 !
b1000 .
b1000 J
b10 '
b10 ,
b10 I
0&
b10101100 (
#173000
b11 !
b11 .
b11 J
1&
b10101101 (
#174000
b0 !
b0 .
b0 J
b11 '
b11 ,
b11 I
0&
b10101110 (
#175000
b1 !
b1 .
b1 J
1&
b10101111 (
#176000
0<
1:
b0 3
08
b1111 2
b1111 -
b1111 4
b1111 H
19
07
b1111 !
b1111 .
b1111 J
b110 #
b110 )
b110 /
b0 '
b0 ,
b0 I
0&
b10110000 (
#177000
1&
b10110001 (
#178000
b1110 !
b1110 .
b1110 J
b1 '
b1 ,
b1 I
0&
b10110010 (
#179000
b111 !
b111 .
b111 J
1&
b10110011 (
#180000
b1100 !
b1100 .
b1100 J
b10 '
b10 ,
b10 I
0&
b10110100 (
#181000
b11 !
b11 .
b11 J
1&
b10110101 (
#182000
b1000 !
b1000 .
b1000 J
b11 '
b11 ,
b11 I
0&
b10110110 (
#183000
b1 !
b1 .
b1 J
1&
b10110111 (
#184000
1"
0G
1F
1B
0C
1A
1=
0>
1<
b111 3
18
b0 -
b0 4
b0 H
09
17
b0 !
b0 .
b0 J
b111 #
b111 )
b111 /
b0 '
b0 ,
b0 I
0&
b10111000 (
#185000
1&
b10111001 (
#186000
b1 '
b1 ,
b1 I
0&
b10111010 (
#187000
1&
b10111011 (
#188000
b10 '
b10 ,
b10 I
0&
b10111100 (
#189000
1&
b10111101 (
#190000
b11 '
b11 ,
b11 I
0&
b10111110 (
#191000
1&
b10111111 (
#192000
0F
0A
0"
0B
0=
0G
0C
0<
0D
0?
0:
05
b0 3
08
b0 2
b0 !
b0 .
b0 J
b0 -
b0 4
b0 H
09
07
b11 %
b11 +
b11 1
b0 #
b0 )
b0 /
b0 '
b0 ,
b0 I
0&
b11000000 (
#193000
1&
b11000001 (
#194000
b1 '
b1 ,
b1 I
0&
b11000010 (
#195000
1&
b11000011 (
#196000
b10 '
b10 ,
b10 I
0&
b11000100 (
#197000
1&
b11000101 (
#198000
b11 '
b11 ,
b11 I
0&
b11000110 (
#199000
1&
b11000111 (
#200000
b1 !
b1 .
b1 J
b1 -
b1 4
b1 H
19
17
b1 #
b1 )
b1 /
b0 '
b0 ,
b0 I
0&
b11001000 (
#201000
1&
b11001001 (
#202000
b10 !
b10 .
b10 J
b1 '
b1 ,
b1 I
0&
b11001010 (
#203000
b0 !
b0 .
b0 J
1&
b11001011 (
#204000
b100 !
b100 .
b100 J
b10 '
b10 ,
b10 I
0&
b11001100 (
#205000
b0 !
b0 .
b0 J
1&
b11001101 (
#206000
b1000 !
b1000 .
b1000 J
b11 '
b11 ,
b11 I
0&
b11001110 (
#207000
b0 !
b0 .
b0 J
1&
b11001111 (
#208000
1>
1:
15
b11 2
b11 -
b11 4
b11 H
19
07
b11 !
b11 .
b11 J
b10 #
b10 )
b10 /
b0 '
b0 ,
b0 I
0&
b11010000 (
#209000
1&
b11010001 (
#210000
b110 !
b110 .
b110 J
b1 '
b1 ,
b1 I
0&
b11010010 (
#211000
b1 !
b1 .
b1 J
1&
b11010011 (
#212000
b1100 !
b1100 .
b1100 J
b10 '
b10 ,
b10 I
0&
b11010100 (
#213000
b0 !
b0 .
b0 J
1&
b11010101 (
#214000
b1000 !
b1000 .
b1000 J
b11 '
b11 ,
b11 I
0&
b11010110 (
#215000
b0 !
b0 .
b0 J
1&
b11010111 (
#216000
1C
1A
1=
0>
1<
b11 3
18
b100 -
b100 4
b100 H
09
17
b100 !
b100 .
b100 J
b11 #
b11 )
b11 /
b0 '
b0 ,
b0 I
0&
b11011000 (
#217000
1&
b11011001 (
#218000
b1000 !
b1000 .
b1000 J
b1 '
b1 ,
b1 I
0&
b11011010 (
#219000
b10 !
b10 .
b10 J
1&
b11011011 (
#220000
b0 !
b0 .
b0 J
b10 '
b10 ,
b10 I
0&
b11011100 (
#221000
b1 !
b1 .
b1 J
1&
b11011101 (
#222000
b0 !
b0 .
b0 J
b11 '
b11 ,
b11 I
0&
b11011110 (
#223000
1&
b11011111 (
#224000
0"
0F
0A
0B
0=
1G
1C
0<
1D
1?
0:
05
b0 3
08
b1100 2
b1100 -
b1100 4
b1100 H
09
07
b1100 !
b1100 .
b1100 J
b100 #
b100 )
b100 /
b0 '
b0 ,
b0 I
0&
b11100000 (
#225000
1&
b11100001 (
#226000
b1000 !
b1000 .
b1000 J
b1 '
b1 ,
b1 I
0&
b11100010 (
#227000
b110 !
b110 .
b110 J
1&
b11100011 (
#228000
b0 !
b0 .
b0 J
b10 '
b10 ,
b10 I
0&
b11100100 (
#229000
b11 !
b11 .
b11 J
1&
b11100101 (
#230000
b0 !
b0 .
b0 J
b11 '
b11 ,
b11 I
0&
b11100110 (
#231000
b1 !
b1 .
b1 J
1&
b11100111 (
#232000
b1101 -
b1101 4
b1101 H
19
17
b1101 !
b1101 .
b1101 J
b101 #
b101 )
b101 /
b0 '
b0 ,
b0 I
0&
b11101000 (
#233000
1&
b11101001 (
#234000
b1010 !
b1010 .
b1010 J
b1 '
b1 ,
b1 I
0&
b11101010 (
#235000
b110 !
b110 .
b110 J
1&
b11101011 (
#236000
b100 !
b100 .
b100 J
b10 '
b10 ,
b10 I
0&
b11101100 (
#237000
b11 !
b11 .
b11 J
1&
b11101101 (
#238000
b1000 !
b1000 .
b1000 J
b11 '
b11 ,
b11 I
0&
b11101110 (
#239000
b1 !
b1 .
b1 J
1&
b11101111 (
#240000
1>
1:
15
b1111 2
b1111 -
b1111 4
b1111 H
19
07
b1111 !
b1111 .
b1111 J
b110 #
b110 )
b110 /
b0 '
b0 ,
b0 I
0&
b11110000 (
#241000
1&
b11110001 (
#242000
b1110 !
b1110 .
b1110 J
b1 '
b1 ,
b1 I
0&
b11110010 (
#243000
b111 !
b111 .
b111 J
1&
b11110011 (
#244000
b1100 !
b1100 .
b1100 J
b10 '
b10 ,
b10 I
0&
b11110100 (
#245000
b11 !
b11 .
b11 J
1&
b11110101 (
#246000
b1000 !
b1000 .
b1000 J
b11 '
b11 ,
b11 I
0&
b11110110 (
#247000
b1 !
b1 .
b1 J
1&
b11110111 (
#248000
1"
0G
1F
1B
0C
1A
1=
0>
1<
b111 3
18
b0 -
b0 4
b0 H
09
17
b0 !
b0 .
b0 J
b111 #
b111 )
b111 /
b0 '
b0 ,
b0 I
0&
b11111000 (
#249000
1&
b11111001 (
#250000
b1 '
b1 ,
b1 I
0&
b11111010 (
#251000
1&
b11111011 (
#252000
b10 '
b10 ,
b10 I
0&
b11111100 (
#253000
1&
b11111101 (
#254000
b11 '
b11 ,
b11 I
0&
b11111110 (
#255000
1&
b11111111 (
#256000
0F
0A
0"
0B
0=
0G
0C
0<
0D
0?
0:
05
b0 3
08
b0 2
b0 !
b0 .
b0 J
b0 -
b0 4
b0 H
09
07
b100 %
b100 +
b100 1
b0 #
b0 )
b0 /
b0 '
b0 ,
b0 I
0&
b100000000 (
#257000
1&
b100000001 (
#258000
b1 '
b1 ,
b1 I
0&
b100000010 (
#259000
1&
b100000011 (
#260000
b10 '
b10 ,
b10 I
0&
b100000100 (
#261000
1&
b100000101 (
#262000
b11 '
b11 ,
b11 I
0&
b100000110 (
#263000
1&
b100000111 (
#264000
b1 !
b1 .
b1 J
b1 -
b1 4
b1 H
19
17
b1 #
b1 )
b1 /
b0 '
b0 ,
b0 I
0&
b100001000 (
#265000
1&
b100001001 (
#266000
b10 !
b10 .
b10 J
b1 '
b1 ,
b1 I
0&
b100001010 (
#267000
b0 !
b0 .
b0 J
1&
b100001011 (
#268000
b100 !
b100 .
b100 J
b10 '
b10 ,
b10 I
0&
b100001100 (
#269000
b0 !
b0 .
b0 J
1&
b100001101 (
#270000
b1000 !
b1000 .
b1000 J
b11 '
b11 ,
b11 I
0&
b100001110 (
#271000
b0 !
b0 .
b0 J
1&
b100001111 (
#272000
1C
1?
b100 2
b100 -
b100 4
b100 H
09
07
b100 !
b100 .
b100 J
b10 #
b10 )
b10 /
b0 '
b0 ,
b0 I
0&
b100010000 (
#273000
1&
b100010001 (
#274000
b1000 !
b1000 .
b1000 J
b1 '
b1 ,
b1 I
0&
b100010010 (
#275000
b10 !
b10 .
b10 J
1&
b100010011 (
#276000
b0 !
b0 .
b0 J
b10 '
b10 ,
b10 I
0&
b100010100 (
#277000
b1 !
b1 .
b1 J
1&
b100010101 (
#278000
b0 !
b0 .
b0 J
b11 '
b11 ,
b11 I
0&
b100010110 (
#279000
1&
b100010111 (
#280000
b101 -
b101 4
b101 H
19
17
b101 !
b101 .
b101 J
b11 #
b11 )
b11 /
b0 '
b0 ,
b0 I
0&
b100011000 (
#281000
1&
b100011001 (
#282000
b1010 !
b1010 .
b1010 J
b1 '
b1 ,
b1 I
0&
b100011010 (
#283000
b10 !
b10 .
b10 J
1&
b100011011 (
#284000
b100 !
b100 .
b100 J
b10 '
b10 ,
b10 I
0&
b100011100 (
#285000
b1 !
b1 .
b1 J
1&
b100011101 (
#286000
b1000 !
b1000 .
b1000 J
b11 '
b11 ,
b11 I
0&
b100011110 (
#287000
b0 !
b0 .
b0 J
1&
b100011111 (
#288000
1G
0C
1>
1D
0?
1:
15
b1011 2
b1011 -
b1011 4
b1011 H
19
07
b1011 !
b1011 .
b1011 J
b100 #
b100 )
b100 /
b0 '
b0 ,
b0 I
0&
b100100000 (
#289000
1&
b100100001 (
#290000
b110 !
b110 .
b110 J
b1 '
b1 ,
b1 I
0&
b100100010 (
#291000
b101 !
b101 .
b101 J
1&
b100100011 (
#292000
b1100 !
b1100 .
b1100 J
b10 '
b10 ,
b10 I
0&
b100100100 (
#293000
b10 !
b10 .
b10 J
1&
b100100101 (
#294000
b1000 !
b1000 .
b1000 J
b11 '
b11 ,
b11 I
0&
b100100110 (
#295000
b1 !
b1 .
b1 J
1&
b100100111 (
#296000
1C
1A
1=
0>
1<
b11 3
18
b1100 -
b1100 4
b1100 H
09
17
b1100 !
b1100 .
b1100 J
b101 #
b101 )
b101 /
b0 '
b0 ,
b0 I
0&
b100101000 (
#297000
1&
b100101001 (
#298000
b1000 !
b1000 .
b1000 J
b1 '
b1 ,
b1 I
0&
b100101010 (
#299000
b110 !
b110 .
b110 J
1&
b100101011 (
#300000
b0 !
b0 .
b0 J
b10 '
b10 ,
b10 I
0&
b100101100 (
#301000
b11 !
b11 .
b11 J
1&
b100101101 (
#302000
b0 !
b0 .
b0 J
b11 '
b11 ,
b11 I
0&
b100101110 (
#303000
b1 !
b1 .
b1 J
1&
b100101111 (
#304000
0"
1G
0A
0F
0=
0B
1C
1>
0<
1?
b0 3
08
b1111 2
b1111 -
b1111 4
b1111 H
19
07
b1111 !
b1111 .
b1111 J
b110 #
b110 )
b110 /
b0 '
b0 ,
b0 I
0&
b100110000 (
#305000
1&
b100110001 (
#306000
b1110 !
b1110 .
b1110 J
b1 '
b1 ,
b1 I
0&
b100110010 (
#307000
b111 !
b111 .
b111 J
1&
b100110011 (
#308000
b1100 !
b1100 .
b1100 J
b10 '
b10 ,
b10 I
0&
b100110100 (
#309000
b11 !
b11 .
b11 J
1&
b100110101 (
#310000
b1000 !
b1000 .
b1000 J
b11 '
b11 ,
b11 I
0&
b100110110 (
#311000
b1 !
b1 .
b1 J
1&
b100110111 (
#312000
1"
0G
1F
1B
0C
1A
1=
0>
1<
b111 3
18
b0 -
b0 4
b0 H
09
17
b0 !
b0 .
b0 J
b111 #
b111 )
b111 /
b0 '
b0 ,
b0 I
0&
b100111000 (
#313000
1&
b100111001 (
#314000
b1 '
b1 ,
b1 I
0&
b100111010 (
#315000
1&
b100111011 (
#316000
b10 '
b10 ,
b10 I
0&
b100111100 (
#317000
1&
b100111101 (
#318000
b11 '
b11 ,
b11 I
0&
b100111110 (
#319000
1&
b100111111 (
#320000
0F
0A
0"
0B
0=
0G
0C
0<
0D
0?
0:
05
b0 3
08
b0 2
b0 !
b0 .
b0 J
b0 -
b0 4
b0 H
09
07
b101 %
b101 +
b101 1
b0 #
b0 )
b0 /
b0 '
b0 ,
b0 I
0&
b101000000 (
#321000
1&
b101000001 (
#322000
b1 '
b1 ,
b1 I
0&
b101000010 (
#323000
1&
b101000011 (
#324000
b10 '
b10 ,
b10 I
0&
b101000100 (
#325000
1&
b101000101 (
#326000
b11 '
b11 ,
b11 I
0&
b101000110 (
#327000
1&
b101000111 (
